heapstream/__init__.py
heapstream/sdk.py
heapstream/hooks/__init__.py
heapstream/hooks/hook.py
heapstream/models/__init__.py
heapstream/models/asset.py
heapstream/models/asset_error.py
heapstream/models/asset_error_type.py
heapstream/models/audio_track.py
heapstream/models/audio_track_create.py
heapstream/models/audio_track_edit.py
heapstream/models/audio_track_list.py
heapstream/models/audio_track_status.py
heapstream/models/audio_track_type.py
heapstream/models/auto_caption.py
heapstream/models/direct_upload_complete_args.py
heapstream/models/direct_upload_list_part.py
heapstream/models/direct_upload_part.py
heapstream/models/direct_upload_response.py
heapstream/models/direct_upload_start.py
heapstream/models/encoding_tier.py
heapstream/models/engagement_stats.py
heapstream/models/engagement_stats_row.py
heapstream/models/multipart_file.py
heapstream/models/only_true_enum.py
heapstream/models/pagination.py
heapstream/models/part_id_response.py
heapstream/models/performance_stats.py
heapstream/models/performance_stats_row.py
heapstream/models/player.py
heapstream/models/player_create.py
heapstream/models/player_edit.py
heapstream/models/player_list.py
heapstream/models/player_logo_position.py
heapstream/models/player_skin.py
heapstream/models/poster.py
heapstream/models/poster_edit.py
heapstream/models/poster_list.py
heapstream/models/preset.py
heapstream/models/preset_list.py
heapstream/models/preset_type.py
heapstream/models/project.py
heapstream/models/project_create.py
heapstream/models/project_edit.py
heapstream/models/project_list.py
heapstream/models/text_track.py
heapstream/models/text_track_create.py
heapstream/models/text_track_edit.py
heapstream/models/text_track_generate.py
heapstream/models/text_track_list.py
heapstream/models/text_track_status.py
heapstream/models/text_track_type.py
heapstream/models/text_track_upload_type.py
heapstream/models/tt_auto_lang.py
heapstream/models/upload_metadata.py
heapstream/models/video.py
heapstream-1.1.0.dist-info/LICENSE
heapstream-1.1.0.dist-info/METADATA
heapstream-1.1.0.dist-info/WHEEL
heapstream-1.1.0.dist-info/top_level.txt
heapstream-1.1.0.dist-info/RECORD
