Metadata-Version: 2.1
Name: heapstream
Version: 1.1.0
Summary:  Explore the API documentation for [Heapstream.com](//heapstream.com)!   ## Authentication   Authentication is done through Basic Authentication [wikipedia](https://en.wikipedia.org/wiki/Basic_access_authentication) [RFC7617](https://datatracker.ietf.org/doc/html/rfc7617). For `username` you should use the `id` of the ApiKey. For `password` you should use the `password` of the ApiKey.  
License: MIT
Project-URL: Homepage, https://heapstream.com
Project-URL: Documentation, https://docs.heapstream.com
Project-URL: Github, https://github.com/heapstream/heapstream-python
Requires-Python: >=3.7
License-File: LICENSE
Requires-Dist: requests>=2.31.0
